[{"_id":"60b6e9fc1ec85acb4193e2c9","characters":[1788,1833,27,252,360,92],"type_name":"Bow","rarity":4,"count":4352},{"_id":"60b6ea101ec85acb4193ed2d","characters":[381,237,82,327,133],"type_name":"Polearm","rarity":5,"count":1160},{"_id":"60b6ea101ec85acb4193ed28","characters":[661,1735,262,96,127,139,29],"type_name":"Claymore","rarity":5,"count":3049},{"_id":"60b6ee421ec85acb41959b34","characters":[19,1594,44,157,68],"type_name":"Bow","rarity":4,"count":1891},{"_id":"60b6e9c91ec85acb4193cc36","characters":[456,424,166,54,43,93],"type_name":"Bow","rarity":4,"count":1236},{"_id":"60b6ec581ec85acb4194cf17","characters":[117,172,56,92,166,42,58],"type_name":"Catalyst","rarity":4,"count":703},{"_id":"60b6e9c91ec85acb4193cc19","characters":[1295,49,11,45,36,24],"type_name":"Catalyst","rarity":4,"count":1467},{"_id":"60b6ec6e1ec85acb4194dbe6","characters":[228,99,341,410,49,175,101,196,15,9,166],"type_name":"Sword","rarity":4,"count":1795},{"_id":"60b6e9c91ec85acb4193cc8a","characters":[1055,490,2303,93,99,41,195,57],"type_name":"Sword","rarity":4,"count":4365},{"_id":"60b6e9c91ec85acb4193cbe6","characters":[1233,111,248,461,355,111,163],"type_name":"Claymore","rarity":4,"count":2682},{"_id":"60b6e9c91ec85acb4193cc2f","characters":[538,720,723,305,45],"type_name":"Bow","rarity":5,"count":2338},{"_id":"60b6ea101ec85acb4193ecba","characters":[584,918,613,225,281,199,131],"type_name":"Catalyst","rarity":4,"count":2951},{"_id":"60b6e9fc1ec85acb4193e2cf","characters":[399,367,322,140,46,31,13],"type_name":"Catalyst","rarity":4,"count":1318},{"_id":"60b6e9fd1ec85acb4193e2df","characters":[1473,93,31,244,48,30,11,26,84,65,19],"type_name":"Sword","rarity":5,"count":2129},{"_id":"60b6ee601ec85acb4195ac8c","characters":[808,436,204,149,54,20,39,50,65,33],"type_name":"Sword","rarity":5,"count":1873},{"_id":"60b6ec6e1ec85acb4194dbe2","characters":[108,2846,1393,96,103,81],"type_name":"Bow","rarity":4,"count":4627},{"_id":"60b6ea101ec85acb4193ecb0","characters":[571,288,1491,282,251,51,64,16,45,111],"type_name":"Sword","rarity":4,"count":3196},{"_id":"60b6e9c91ec85acb4193cc61","characters":[3909,680,341,268,43,160,145,154,66,109,33,159],"type_name":"Sword","rarity":4,"count":6067},{"_id":"60b6e9c91ec85acb4193cc09","characters":[839,974,319,34,38],"type_name":"Polearm","rarity":4,"count":2204},{"_id":"60b6e9c91ec85acb4193cc66","characters":[866,143,106,242,55,125,22,93,37,145,259,82],"type_name":"Sword","rarity":4,"count":2175},{"_id":"60b6e9c91ec85acb4193cbdd","characters":[2401,176,15,17],"type_name":"Claymore","rarity":4,"count":2633},{"_id":"60b6ec581ec85acb4194cee4","characters":[100,660,163,136,248,56,15],"type_name":"Claymore","rarity":4,"count":1378},{"_id":"60b6e9fc1ec85acb4193e2c3","characters":[3447,365,687,75,42,120,61],"type_name":"Catalyst","rarity":3,"count":4797},{"_id":"60b6e9c91ec85acb4193cbf7","characters":[1214,33,568,21],"type_name":"Polearm","rarity":4,"count":1842},{"_id":"60b6ea101ec85acb4193ecb6","characters":[73,325,917,155,45,39,36,14,22,82],"type_name":"Sword","rarity":4,"count":1718},{"_id":"60b6e9fc1ec85acb4193e2cd","characters":[1774,284,28,29,17],"type_name":"Polearm","rarity":5,"count":2132},{"_id":"60b6e9c91ec85acb4193cbfd","characters":[3867,237,40,42,127],"type_name":"Bow","rarity":4,"count":4319},{"_id":"60b6e9fd1ec85acb4193e2e4","characters":[521,699,194,390,115,168,37],"type_name":"Claymore","rarity":4,"count":2124},{"_id":"60b6ea101ec85acb4193ed15","characters":[1154,632,25,36,63,93],"type_name":"Bow","rarity":4,"count":2003},{"_id":"60b6ea101ec85acb4193ed20","characters":[32,169,227,56,56,405,92],"type_name":"Catalyst","rarity":5,"count":1037},{"_id":"60b6e9fc1ec85acb4193e2ca","characters":[2326,76,101,133,80,16],"type_name":"Bow","rarity":5,"count":2732},{"_id":"60b6ee601ec85acb4195aca1","characters":[807,30,32],"type_name":"Claymore","rarity":5,"count":877},{"_id":"60b6ec6e1ec85acb4194dbdf","characters":[70,795,324,63,142,175,80,27,10,13,60,67],"type_name":"Sword","rarity":4,"count":1826},{"_id":"60b6efc51ec85acb4196495a","characters":[55,222,265,465,122,28,38],"type_name":"Catalyst","rarity":4,"count":1195},{"_id":"60b6ea101ec85acb4193ecb2","characters":[1562,24,16,11],"type_name":"Polearm","rarity":3,"count":1616},{"_id":"60b6ef7d1ec85acb41962403","characters":[240,136,109,354,63,44,13],"type_name":"Claymore","rarity":4,"count":959},{"_id":"60b6ea101ec85acb4193ecb4","characters":[1000,235,393,145,68,17,48],"type_name":"Catalyst","rarity":5,"count":1906},{"_id":"60b6ee931ec85acb4195c709","characters":[385,306,27,88,28],"type_name":"Polearm","rarity":4,"count":834},{"_id":"60b6ef561ec85acb419611aa","characters":[4067,61,176,33,37,24,73],"type_name":"Catalyst","rarity":4,"count":4471},{"_id":"60b6ee421ec85acb41959b7b","characters":[785,34,56,45,25,26,32,16,36,8,15,24],"type_name":"Sword","rarity":3,"count":1102},{"_id":"60b6ee421ec85acb41959b68","characters":[439,247,194,278,66,20],"type_name":"Bow","rarity":4,"count":1244},{"_id":"60b6e9c91ec85acb4193cc0c","characters":[302,394,403,111,95,132,44],"type_name":"Claymore","rarity":5,"count":1481},{"_id":"60b6ee931ec85acb4195c702","characters":[714,959,192,185,231],"type_name":"Polearm","rarity":4,"count":2281},{"_id":"60b6e9c91ec85acb4193cc4a","characters":[697,349,153,69,94,54,41],"type_name":"Claymore","rarity":4,"count":1457},{"_id":"60b6e9fd1ec85acb4193e317","characters":[454,109,76,345,117],"type_name":"Polearm","rarity":5,"count":1101},{"_id":"60b6fe3f1ec85acb419c42f4","characters":[53,42,25,26,32,52,10,1359,29],"type_name":"Sword","rarity":4,"count":1644},{"_id":"60b6ec581ec85acb4194cee0","characters":[149,664,125,37,157,37,57],"type_name":"Catalyst","rarity":4,"count":1226},{"_id":"60ca923d1ec85acb4187dea8","characters":[641,614,27,76,85,34,45],"type_name":"Catalyst","rarity":4,"count":1522}]