{"char_id":"60b6eda01ec85acb41954e1b","constellations":[26,64,175,319,377,367,2703],"builds":[{"weapons":[{"_id":"60b6ec6e1ec85acb4194dbe2","count":683},{"_id":"60b6ea101ec85acb4193ed15","count":224},{"_id":"60b6e9c91ec85acb4193cc36","count":198},{"_id":"60b6e9fc1ec85acb4193e2c9","count":123},{"_id":"60b6e9c91ec85acb4193cc2f","count":122},{"_id":"60b6ee421ec85acb41959b68","count":96},{"_id":"60b6e9c91ec85acb4193cbfd","count":57},{"_id":"60b6e9fc1ec85acb4193e2ca","count":52},{"_id":"60b6e9c91ec85acb4193cc05","count":47},{"_id":"60b6ef7d1ec85acb419623ce","count":38},{"_id":"60c094211ec85acb41ebcc63","count":32},{"_id":"60b6ee421ec85acb41959b34","count":27},{"_id":"60b6f3401ec85acb4197c9cd","count":13},{"_id":"60b6ee921ec85acb4195c6e2","count":10}],"artifacts":[{"_id":"60b6e9c91ec85acb4193cc75","activation_number":4}],"count":1733},{"weapons":[{"_id":"60b6ec6e1ec85acb4194dbe2","count":321},{"_id":"60b6e9c91ec85acb4193cc2f","count":83},{"_id":"60b6e9fc1ec85acb4193e2c9","count":67},{"_id":"60b6e9c91ec85acb4193cc36","count":56},{"_id":"60b6ea101ec85acb4193ed15","count":48},{"_id":"60b6e9c91ec85acb4193cc05","count":36},{"_id":"60b6f3401ec85acb4197c9cd","count":32},{"_id":"60b6e9c91ec85acb4193cbfd","count":30},{"_id":"60b6ee421ec85acb41959b68","count":25},{"_id":"60b6e9fc1ec85acb4193e2ca","count":10},{"_id":"60c094211ec85acb41ebcc63","count":10},{"_id":"60b6ee421ec85acb41959b34","count":7},{"_id":"60b6ef7d1ec85acb419623ce","count":5}],"artifacts":[{"_id":"60b6e9c91ec85acb4193cf13","activation_number":4}],"count":740},{"weapons":[{"_id":"60b6ec6e1ec85acb4194dbe2","count":112},{"_id":"60b6ea101ec85acb4193ed15","count":61},{"_id":"60b6e9c91ec85acb4193cc2f","count":38},{"_id":"60b6e9c91ec85acb4193cc36","count":25},{"_id":"60b6e9fc1ec85acb4193e2ca","count":22},{"_id":"60b6e9fc1ec85acb4193e2c9","count":19},{"_id":"60b6ee421ec85acb41959b68","count":15},{"_id":"60b6e9c91ec85acb4193cc05","count":9},{"_id":"60b6ef7d1ec85acb419623ce","count":8},{"_id":"60b6e9c91ec85acb4193cbfd","count":4},{"_id":"60c094211ec85acb41ebcc63","count":4},{"_id":"60b6f8a31ec85acb4199ece5","count":3},{"_id":"60b6f3401ec85acb4197c9cd","count":3}],"artifacts":[{"_id":"60b6e9c91ec85acb4193cc75","activation_number":2},{"_id":"60b6e9c91ec85acb4193cca6","activation_number":2}],"count":328},{"weapons":[{"_id":"60b6ec6e1ec85acb4194dbe2","count":94},{"_id":"60b6ea101ec85acb4193ed15","count":49},{"_id":"60b6e9fc1ec85acb4193e2c9","count":25},{"_id":"60b6e9c91ec85acb4193cc2f","count":21},{"_id":"60b6e9c91ec85acb4193cc36","count":21},{"_id":"60b6e9fc1ec85acb4193e2ca","count":19},{"_id":"60b6ee421ec85acb41959b68","count":15},{"_id":"60b6ef7d1ec85acb419623ce","count":12},{"_id":"60c094211ec85acb41ebcc63","count":8},{"_id":"60b6e9c91ec85acb4193cc05","count":7},{"_id":"60b6ee421ec85acb41959b34","count":7},{"_id":"60b6e9c91ec85acb4193cbfd","count":4}],"artifacts":[{"_id":"60b6e9fe1ec85acb4193e646","activation_number":4}],"count":288},{"weapons":[{"_id":"60b6ea101ec85acb4193ed15","count":53},{"_id":"60c094211ec85acb41ebcc63","count":36},{"_id":"60b6e9c91ec85acb4193cc2f","count":34},{"_id":"60b6ef7d1ec85acb419623ce","count":22},{"_id":"60b6ec6e1ec85acb4194dbe2","count":7},{"_id":"60b6ee421ec85acb41959b68","count":7},{"_id":"60b6e9fc1ec85acb4193e2ca","count":6},{"_id":"60b6e9c91ec85acb4193cc36","count":4}],"artifacts":[{"_id":"60b6e9fd1ec85acb4193e2e7","activation_number":4}],"count":176},{"weapons":[{"_id":"60b6ea101ec85acb4193ed15","count":61},{"_id":"60b6e9c91ec85acb4193cc2f","count":29},{"_id":"60b6ef7d1ec85acb419623ce","count":29},{"_id":"60b6e9fc1ec85acb4193e2ca","count":7},{"_id":"60b6ee421ec85acb41959b68","count":5},{"_id":"60b6e9fc1ec85acb4193e2c9","count":5},{"_id":"60c094211ec85acb41ebcc63","count":5},{"_id":"60b6e9c91ec85acb4193cc36","count":4},{"_id":"60b6ec6e1ec85acb4194dbe2","count":3}],"artifacts":[{"_id":"60b6e9c91ec85acb4193cca6","activation_number":2},{"_id":"60b6e9c91ec85acb4193cf3d","activation_number":2}],"count":152},{"weapons":[{"_id":"60b6ec6e1ec85acb4194dbe2","count":37},{"_id":"60b6ea101ec85acb4193ed15","count":20},{"_id":"60b6e9c91ec85acb4193cc36","count":17},{"_id":"60b6e9fc1ec85acb4193e2ca","count":13},{"_id":"60b6e9fc1ec85acb4193e2c9","count":11},{"_id":"60b6ee421ec85acb41959b68","count":8},{"_id":"60b6ee421ec85acb41959b34","count":8},{"_id":"60b6e9c91ec85acb4193cc2f","count":6},{"_id":"60c094211ec85acb41ebcc63","count":5},{"_id":"60b6e9c91ec85acb4193cbfd","count":5},{"_id":"60b6ef7d1ec85acb419623ce","count":4}],"artifacts":[{"_id":"60b6e9ca1ec85acb4193d041","activation_number":4}],"count":137},{"weapons":[{"_id":"60b6ec6e1ec85acb4194dbe2","count":39},{"_id":"60b6e9c91ec85acb4193cc36","count":9},{"_id":"60b6ea101ec85acb4193ed15","count":7},{"_id":"60b6e9fc1ec85acb4193e2ca","count":5},{"_id":"60b6e9c91ec85acb4193cc2f","count":5},{"_id":"60b6ee421ec85acb41959b68","count":3},{"_id":"60b6ef7d1ec85acb419623ce","count":3}],"artifacts":[{"_id":"60b6e9c91ec85acb4193cc75","activation_number":2},{"_id":"60b6e9ca1ec85acb4193d041","activation_number":2}],"count":82},{"weapons":[{"_id":"60b6ec6e1ec85acb4194dbe2","count":21},{"_id":"60b6ea101ec85acb4193ed15","count":15},{"_id":"60b6e9c91ec85acb4193cc36","count":8},{"_id":"60b6e9c91ec85acb4193cc2f","count":6},{"_id":"60b6ee421ec85acb41959b68","count":4},{"_id":"60b6e9fc1ec85acb4193e2ca","count":4},{"_id":"60b6e9fc1ec85acb4193e2c9","count":3},{"_id":"60b6ef7d1ec85acb419623ce","count":3}],"artifacts":[{"_id":"60b6e9c91ec85acb4193cca6","activation_number":2},{"_id":"60b6e9ca1ec85acb4193d041","activation_number":2}],"count":69},{"weapons":[{"_id":"60b6ea101ec85acb4193ed15","count":14},{"_id":"60b6ec6e1ec85acb4194dbe2","count":10},{"_id":"60b6e9c91ec85acb4193cc36","count":8},{"_id":"60b6e9c91ec85acb4193cc2f","count":6},{"_id":"60b6ee421ec85acb41959b68","count":5},{"_id":"60b6e9fc1ec85acb4193e2ca","count":4},{"_id":"60b6ef7d1ec85acb419623ce","count":4}],"artifacts":[{"_id":"60b6e9c91ec85acb4193cca6","activation_number":4}],"count":57},{"weapons":[{"_id":"60b6ec6e1ec85acb4194dbe2","count":16},{"_id":"60b6e9fc1ec85acb4193e2c9","count":7},{"_id":"60b6ea101ec85acb4193ed15","count":7},{"_id":"60b6e9c91ec85acb4193cc36","count":6}],"artifacts":[{"_id":"60b6e9c91ec85acb4193cc4e","activation_number":4}],"count":47},{"weapons":[{"_id":"60b6ec6e1ec85acb4194dbe2","count":7},{"_id":"60b6e9fc1ec85acb4193e2c9","count":4}],"artifacts":[{"_id":"60b6ec581ec85acb4194cf46","activation_number":4}],"count":20}],"teams":[{"party":["60b6eda01ec85acb41954e1b","60b6eda01ec85acb41954e7d","60b6ede91ec85acb41957255","60b6ede91ec85acb4195729c"],"count":515},{"party":["60b6eda01ec85acb41954e1b","60b6eda01ec85acb41954e4e","60b6eda01ec85acb41954e7d","60b6ede91ec85acb41957255"],"count":338},{"party":["60b6eda01ec85acb41954e1b","60b6eda01ec85acb41954e4e","60b6ede91ec85acb41957255","60b6ede91ec85acb4195729c"],"count":337},{"party":["60b6eda01ec85acb41954e1b","60b6eda01ec85acb41954e4e","60b6eda01ec85acb41954ed9","60b6ede91ec85acb41957255"],"count":305},{"party":["60b6eda01ec85acb41954e1b","60b6eda01ec85acb41954e37","60b6edd41ec85acb419565c6","60b6ede91ec85acb4195729c"],"count":227},{"party":["60b6eda01ec85acb41954df1","60b6eda01ec85acb41954e1b","60b6eda01ec85acb41954e7d","60b6eda01ec85acb41954ed9"],"count":209},{"party":["60b6eda01ec85acb41954e1b","60b6eda01ec85acb41954e4e","60b6eda01ec85acb41954e99","60b6ede91ec85acb41957255"],"count":208},{"party":["60b6eda01ec85acb41954e1b","60b6eda01ec85acb41954e37","60b6eda01ec85acb41954e4e","60b6ede91ec85acb41957255"],"count":199},{"party":["60b6eda01ec85acb41954e1b","60b6eda01ec85acb41954e7d","60b6eda01ec85acb41954ed9","60b6ede91ec85acb41957255"],"count":193},{"party":["60b6eda01ec85acb41954e1b","60b6eda01ec85acb41954e37","60b6eda01ec85acb41954e99","60b6ede91ec85acb4195725a"],"count":189},{"party":["60b6eda01ec85acb41954e1b","60b6eda01ec85acb41954e4e","60b6eda01ec85acb41954ed9","60b6ede91ec85acb41957239"],"count":182},{"party":["60b6eda01ec85acb41954df1","60b6eda01ec85acb41954e1b","60b6eda01ec85acb41954e37","60b6eda01ec85acb41954e7d"],"count":179},{"party":["60b6eda01ec85acb41954e1b","60b6eda01ec85acb41954e4e","60b6ede91ec85acb41957255","60b6ede91ec85acb4195725a"],"count":173},{"party":["60b6eda01ec85acb41954e1b","60b6eda01ec85acb41954e7d","60b6ede91ec85acb41957239","60b6ede91ec85acb4195729c"],"count":163},{"party":["60b6eda01ec85acb41954e1b","60b6ede91ec85acb41957206","60b6ede91ec85acb41957255","60b6ede91ec85acb4195729c"],"count":150},{"party":["60b6eda01ec85acb41954e1b","60b6eda01ec85acb41954e7d","60b6ede91ec85acb419571ea","60b6ede91ec85acb4195729c"],"count":142},{"party":["60b6eda01ec85acb41954e1b","60b6eda01ec85acb41954e4e","60b6eda01ec85acb41954e6e","60b6ede91ec85acb41957255"],"count":138},{"party":["60b6eda01ec85acb41954df1","60b6eda01ec85acb41954e1b","60b6eda01ec85acb41954e7d","60b6ede91ec85acb4195729c"],"count":137},{"party":["60b6eda01ec85acb41954df1","60b6eda01ec85acb41954e1b","60b6eda01ec85acb41954e4e","60b6eda01ec85acb41954ed9"],"count":137},{"party":["60b6eda01ec85acb41954e1b","60b6eda01ec85acb41954ed9","60b6ede91ec85acb41957255","60b6ede91ec85acb4195729c"],"count":134},{"party":["60b6eda01ec85acb41954e1b","60b6eda01ec85acb41954ec0","60b6ede91ec85acb41957255","60b6ede91ec85acb4195729c"],"count":134},{"party":["60b6eda01ec85acb41954e1b","60b6eda01ec85acb41954e7d","60b6eda01ec85acb41954ed9","60b6ede91ec85acb41957239"],"count":131},{"party":["60b6eda01ec85acb41954e1b","60b6edd41ec85acb4195658b","60b6ede91ec85acb41957255","60b6ede91ec85acb4195729c"],"count":131}],"total":3829}