{"characterId":"61125ec7d183b274dd8a3ec1","all":{"constellations":[13543,1201,386,72,38,8,191],"builds":[{"count":8866,"artifactSetBuildId":"61954db1a48a6ff6cf3e0862","weapons":[{"weaponId":"60b6ea101ec85acb4193ed15","count":4369},{"weaponId":"611258a2d183b274dd8906a4","count":1766},{"weaponId":"60b6e9c91ec85acb4193cc2f","count":819},{"weaponId":"60b6e9fc1ec85acb4193e2ca","count":596},{"weaponId":"6103e6cbaa0079ac7260ef61","count":493},{"weaponId":"60b6ee421ec85acb41959b68","count":263},{"weaponId":"60b6ee921ec85acb4195c6e2","count":141},{"weaponId":"60b6ee421ec85acb41959b34","count":81},{"weaponId":"60b6e9c91ec85acb4193cc36","count":58},{"weaponId":"60b6ec6e1ec85acb4194dbe2","count":55}]},{"count":2797,"artifactSetBuildId":"61954db5a48a6ff6cf3e09c2","weapons":[{"weaponId":"60b6ea101ec85acb4193ed15","count":1342},{"weaponId":"611258a2d183b274dd8906a4","count":367},{"weaponId":"60b6e9c91ec85acb4193cc2f","count":305},{"weaponId":"60b6e9fc1ec85acb4193e2ca","count":214},{"weaponId":"6103e6cbaa0079ac7260ef61","count":205},{"weaponId":"60b6ee421ec85acb41959b68","count":100},{"weaponId":"60b6ee921ec85acb4195c6e2","count":57},{"weaponId":"60b6ee421ec85acb41959b34","count":41},{"weaponId":"60b6ec6e1ec85acb4194dbe2","count":40},{"weaponId":"60b6e9c91ec85acb4193cc36","count":38}]},{"count":1019,"artifactSetBuildId":"61954db1a48a6ff6cf3e0838","weapons":[{"weaponId":"60b6ea101ec85acb4193ed15","count":526},{"weaponId":"611258a2d183b274dd8906a4","count":131},{"weaponId":"6103e6cbaa0079ac7260ef61","count":92},{"weaponId":"60b6e9c91ec85acb4193cc2f","count":80},{"weaponId":"60b6e9fc1ec85acb4193e2ca","count":74},{"weaponId":"60b6ee421ec85acb41959b68","count":31},{"weaponId":"60b6ee921ec85acb4195c6e2","count":16},{"weaponId":"60b6ec6e1ec85acb4194dbe2","count":15},{"weaponId":"60b6e9c91ec85acb4193cc36","count":14},{"weaponId":"60b6ee421ec85acb41959b34","count":10}]},{"count":687,"artifactSetBuildId":"61954db5a48a6ff6cf3e0ae3","weapons":[{"weaponId":"60b6ea101ec85acb4193ed15","count":335},{"weaponId":"611258a2d183b274dd8906a4","count":126},{"weaponId":"60b6e9c91ec85acb4193cc2f","count":56},{"weaponId":"60b6e9fc1ec85acb4193e2ca","count":53},{"weaponId":"6103e6cbaa0079ac7260ef61","count":47},{"weaponId":"60b6ee421ec85acb41959b68","count":20},{"weaponId":"60b6ee421ec85acb41959b34","count":13},{"weaponId":"60b6e9c91ec85acb4193cc36","count":7},{"weaponId":"60b6ee921ec85acb4195c6e2","count":7},{"weaponId":"616644a7d28d8641387f7aaa","count":6}]},{"count":426,"artifactSetBuildId":"61954db7a48a6ff6cf3e0d0f","weapons":[{"weaponId":"60b6ea101ec85acb4193ed15","count":190},{"weaponId":"611258a2d183b274dd8906a4","count":83},{"weaponId":"6103e6cbaa0079ac7260ef61","count":50},{"weaponId":"60b6e9c91ec85acb4193cc2f","count":35},{"weaponId":"60b6e9fc1ec85acb4193e2ca","count":26},{"weaponId":"60b6ee421ec85acb41959b68","count":12},{"weaponId":"60b6ec6e1ec85acb4194dbe2","count":8},{"weaponId":"60b6ee421ec85acb41959b34","count":6},{"weaponId":"616644a7d28d8641387f7aaa","count":4},{"weaponId":"60b6ee921ec85acb4195c6e2","count":4}]},{"count":222,"artifactSetBuildId":"61954db1a48a6ff6cf3e0812","weapons":[{"weaponId":"60b6ea101ec85acb4193ed15","count":92},{"weaponId":"60b6e9c91ec85acb4193cc2f","count":27},{"weaponId":"6103e6cbaa0079ac7260ef61","count":24},{"weaponId":"611258a2d183b274dd8906a4","count":20},{"weaponId":"60b6e9fc1ec85acb4193e2ca","count":16},{"weaponId":"60b6ee421ec85acb41959b68","count":12},{"weaponId":"60b6e9fc1ec85acb4193e2c9","count":6},{"weaponId":"60b6ec6e1ec85acb4194dbe2","count":6},{"weaponId":"60b6ee421ec85acb41959b34","count":4},{"weaponId":"60b6e9c91ec85acb4193cc36","count":4}]},{"count":203,"artifactSetBuildId":"61954db8a48a6ff6cf3e0ed9","weapons":[{"weaponId":"60b6ea101ec85acb4193ed15","count":117},{"weaponId":"611258a2d183b274dd8906a4","count":19},{"weaponId":"60b6e9c91ec85acb4193cc2f","count":12},{"weaponId":"60b6e9fc1ec85acb4193e2ca","count":12},{"weaponId":"6103e6cbaa0079ac7260ef61","count":11},{"weaponId":"60b6ee421ec85acb41959b68","count":6},{"weaponId":"60b6ee421ec85acb41959b34","count":6},{"weaponId":"60b6ec6e1ec85acb4194dbe2","count":4},{"weaponId":"616644a7d28d8641387f7aaa","count":4},{"weaponId":"60b6e9fc1ec85acb4193e2c9","count":3}]},{"count":154,"artifactSetBuildId":"61954db6a48a6ff6cf3e0b73","weapons":[{"weaponId":"60b6ea101ec85acb4193ed15","count":90},{"weaponId":"611258a2d183b274dd8906a4","count":12},{"weaponId":"6103e6cbaa0079ac7260ef61","count":10},{"weaponId":"60b6ee421ec85acb41959b68","count":9},{"weaponId":"60b6e9c91ec85acb4193cc2f","count":7},{"weaponId":"60b6e9fc1ec85acb4193e2ca","count":6},{"weaponId":"60b6ee421ec85acb41959b34","count":5},{"weaponId":"60b6ee921ec85acb4195c6e2","count":4},{"weaponId":"60b6f8a31ec85acb4199ece5","count":2},{"weaponId":"60b6ef7d1ec85acb419623ce","count":2}]},{"count":127,"artifactSetBuildId":"61954db6a48a6ff6cf3e0b86","weapons":[{"weaponId":"60b6ea101ec85acb4193ed15","count":55},{"weaponId":"611258a2d183b274dd8906a4","count":15},{"weaponId":"60b6e9c91ec85acb4193cc2f","count":14},{"weaponId":"6103e6cbaa0079ac7260ef61","count":13},{"weaponId":"60b6e9fc1ec85acb4193e2ca","count":10},{"weaponId":"60b6e9fc1ec85acb4193e2c9","count":5},{"weaponId":"60b6ee421ec85acb41959b34","count":4},{"weaponId":"60b6e9c91ec85acb4193cc36","count":3},{"weaponId":"60b6ec6e1ec85acb4194dbe2","count":3},{"weaponId":"60b6ee921ec85acb4195c6e2","count":2}]},{"count":122,"artifactSetBuildId":"61954db5a48a6ff6cf3e0a1f","weapons":[{"weaponId":"60b6ea101ec85acb4193ed15","count":55},{"weaponId":"611258a2d183b274dd8906a4","count":16},{"weaponId":"60b6e9c91ec85acb4193cc2f","count":10},{"weaponId":"6103e6cbaa0079ac7260ef61","count":10},{"weaponId":"60b6e9fc1ec85acb4193e2ca","count":9},{"weaponId":"60b6ee421ec85acb41959b68","count":5},{"weaponId":"60b6f8a31ec85acb4199ece5","count":4},{"weaponId":"60b6ec6e1ec85acb4194dbe2","count":4},{"weaponId":"60b6ee921ec85acb4195c6e2","count":3},{"weaponId":"60b6e9c91ec85acb4193cc36","count":3}]}],"total":15439},"abyss":{"constellations":[23601,2222,800,141,92,12,442],"builds":[{"battleCount":16704,"winCount":14605,"artifactSetBuildId":"61954db1a48a6ff6cf3e0862","totalStars":47534,"weapons":[{"weaponId":"60b6ea101ec85acb4193ed15","battleCount":8217,"avgStar":2.837045150298162,"winCount":7131,"star":23312},{"weaponId":"611258a2d183b274dd8906a4","battleCount":4047,"avgStar":2.897454904867803,"winCount":3700,"star":11726},{"weaponId":"60b6e9c91ec85acb4193cc2f","battleCount":1731,"avgStar":2.827845176198729,"winCount":1487,"star":4895},{"weaponId":"60b6e9fc1ec85acb4193e2ca","battleCount":1122,"avgStar":2.839572192513369,"winCount":974,"star":3186},{"weaponId":"6103e6cbaa0079ac7260ef61","battleCount":654,"avgStar":2.753822629969419,"winCount":525,"star":1801},{"weaponId":"60b6ee421ec85acb41959b68","battleCount":378,"avgStar":2.822751322751323,"winCount":325,"star":1067},{"weaponId":"60b6ee921ec85acb4195c6e2","battleCount":198,"avgStar":2.742424242424242,"winCount":161,"star":543},{"weaponId":"60b6e9c91ec85acb4193cc36","battleCount":63,"avgStar":2.8253968253968256,"winCount":54,"star":178},{"weaponId":"60b6ee421ec85acb41959b34","battleCount":60,"avgStar":2.9,"winCount":55,"star":174},{"weaponId":"60b6f8a31ec85acb4199ece5","battleCount":53,"avgStar":2.7358490566037736,"winCount":42,"star":145}]},{"battleCount":5203,"winCount":4453,"artifactSetBuildId":"61954db5a48a6ff6cf3e09c2","totalStars":14689,"weapons":[{"weaponId":"60b6ea101ec85acb4193ed15","battleCount":2412,"avgStar":2.8217247097844114,"winCount":2062,"star":6806},{"weaponId":"611258a2d183b274dd8906a4","battleCount":1075,"avgStar":2.878139534883721,"winCount":970,"star":3094},{"weaponId":"60b6e9c91ec85acb4193cc2f","battleCount":589,"avgStar":2.796264855687606,"winCount":489,"star":1647},{"weaponId":"60b6e9fc1ec85acb4193e2ca","battleCount":390,"avgStar":2.8025641025641024,"winCount":325,"star":1093},{"weaponId":"6103e6cbaa0079ac7260ef61","battleCount":305,"avgStar":2.7573770491803278,"winCount":246,"star":841},{"weaponId":"60b6ee421ec85acb41959b68","battleCount":123,"avgStar":2.821138211382114,"winCount":103,"star":347},{"weaponId":"60b6ee921ec85acb4195c6e2","battleCount":91,"avgStar":2.791208791208791,"winCount":78,"star":254},{"weaponId":"60b6ec6e1ec85acb4194dbe2","battleCount":39,"avgStar":2.8461538461538463,"winCount":34,"star":111},{"weaponId":"60b6e9fc1ec85acb4193e2c9","battleCount":35,"avgStar":2.7142857142857144,"winCount":28,"star":95},{"weaponId":"60b6ee421ec85acb41959b34","battleCount":34,"avgStar":2.823529411764706,"winCount":28,"star":96}]},{"battleCount":2200,"winCount":1930,"artifactSetBuildId":"61954db1a48a6ff6cf3e0838","totalStars":6260,"weapons":[{"weaponId":"60b6ea101ec85acb4193ed15","battleCount":1111,"avgStar":2.867686768676868,"winCount":994,"star":3186},{"weaponId":"611258a2d183b274dd8906a4","battleCount":290,"avgStar":2.910344827586207,"winCount":269,"star":844},{"weaponId":"60b6e9c91ec85acb4193cc2f","battleCount":250,"avgStar":2.872,"winCount":224,"star":718},{"weaponId":"6103e6cbaa0079ac7260ef61","battleCount":218,"avgStar":2.743119266055046,"winCount":177,"star":598},{"weaponId":"60b6e9fc1ec85acb4193e2ca","battleCount":179,"avgStar":2.8268156424581004,"winCount":154,"star":506},{"weaponId":"60b6ee421ec85acb41959b68","battleCount":74,"avgStar":2.7567567567567566,"winCount":60,"star":204},{"weaponId":"60b6ef7d1ec85acb419623ce","battleCount":20,"avgStar":2.75,"winCount":16,"star":55},{"weaponId":"60b6ee921ec85acb4195c6e2","battleCount":19,"avgStar":2.263157894736842,"winCount":8,"star":43},{"weaponId":"60b6ee421ec85acb41959b34","battleCount":7,"avgStar":3,"winCount":7,"star":21},{"weaponId":"60b72bf91ec85acb41af3af0","battleCount":6,"avgStar":2.8333333333333335,"winCount":5,"star":17}]},{"battleCount":730,"winCount":640,"artifactSetBuildId":"61954db5a48a6ff6cf3e0ae3","totalStars":2084,"weapons":[{"weaponId":"60b6ea101ec85acb4193ed15","battleCount":345,"avgStar":2.8318840579710143,"winCount":297,"star":977},{"weaponId":"611258a2d183b274dd8906a4","battleCount":153,"avgStar":2.915032679738562,"winCount":142,"star":446},{"weaponId":"60b6e9c91ec85acb4193cc2f","battleCount":72,"avgStar":2.875,"winCount":65,"star":207},{"weaponId":"60b6e9fc1ec85acb4193e2ca","battleCount":60,"avgStar":2.816666666666667,"winCount":49,"star":169},{"weaponId":"6103e6cbaa0079ac7260ef61","battleCount":53,"avgStar":2.7358490566037736,"winCount":41,"star":145},{"weaponId":"60b6ee421ec85acb41959b68","battleCount":21,"avgStar":2.9523809523809526,"winCount":20,"star":62},{"weaponId":"60b6ee421ec85acb41959b34","battleCount":20,"avgStar":3,"winCount":20,"star":60},{"weaponId":"60b6ef7d1ec85acb419623ce","battleCount":3,"avgStar":3,"winCount":3,"star":9},{"weaponId":"60b6ee921ec85acb4195c6e2","battleCount":3,"avgStar":3,"winCount":3,"star":9}]},{"battleCount":411,"winCount":350,"artifactSetBuildId":"61954db7a48a6ff6cf3e0d0f","totalStars":1163,"weapons":[{"weaponId":"60b6ea101ec85acb4193ed15","battleCount":196,"avgStar":2.816326530612245,"winCount":164,"star":552},{"weaponId":"611258a2d183b274dd8906a4","battleCount":62,"avgStar":2.9516129032258065,"winCount":59,"star":183},{"weaponId":"60b6e9c91ec85acb4193cc2f","battleCount":58,"avgStar":2.8448275862068964,"winCount":49,"star":165},{"weaponId":"6103e6cbaa0079ac7260ef61","battleCount":50,"avgStar":2.66,"winCount":37,"star":133},{"weaponId":"60b6e9fc1ec85acb4193e2ca","battleCount":29,"avgStar":2.8620689655172415,"winCount":26,"star":83},{"weaponId":"60b6ee421ec85acb41959b68","battleCount":5,"avgStar":2.8,"winCount":4,"star":14},{"weaponId":"60b6ec6e1ec85acb4194dbe2","battleCount":3,"avgStar":3,"winCount":3,"star":9},{"weaponId":"60b6ee421ec85acb41959b34","battleCount":3,"avgStar":3,"winCount":3,"star":9},{"weaponId":"60b6e9c91ec85acb4193cc36","battleCount":3,"avgStar":3,"winCount":3,"star":9},{"weaponId":"616644a7d28d8641387f7aaa","battleCount":2,"avgStar":3,"winCount":2,"star":6}]},{"battleCount":337,"winCount":275,"artifactSetBuildId":"61954db1a48a6ff6cf3e0812","totalStars":937,"weapons":[{"weaponId":"60b6ea101ec85acb4193ed15","battleCount":126,"avgStar":2.7857142857142856,"winCount":103,"star":351},{"weaponId":"611258a2d183b274dd8906a4","battleCount":56,"avgStar":2.9464285714285716,"winCount":53,"star":165},{"weaponId":"60b6e9c91ec85acb4193cc2f","battleCount":56,"avgStar":2.607142857142857,"winCount":39,"star":146},{"weaponId":"60b6ee421ec85acb41959b68","battleCount":33,"avgStar":2.787878787878788,"winCount":27,"star":92},{"weaponId":"6103e6cbaa0079ac7260ef61","battleCount":31,"avgStar":2.806451612903226,"winCount":26,"star":87},{"weaponId":"60b6ee421ec85acb41959b34","battleCount":17,"avgStar":2.9411764705882355,"winCount":16,"star":50},{"weaponId":"60b6e9fc1ec85acb4193e2ca","battleCount":8,"avgStar":2.25,"winCount":3,"star":18},{"weaponId":"60b6e9c91ec85acb4193cbfd","battleCount":4,"avgStar":2.75,"winCount":3,"star":11},{"weaponId":"60b6ec6e1ec85acb4194dbe2","battleCount":3,"avgStar":2.6666666666666665,"winCount":2,"star":8},{"weaponId":"60b6ee921ec85acb4195c6e2","battleCount":3,"avgStar":3,"winCount":3,"star":9}]},{"battleCount":175,"winCount":146,"artifactSetBuildId":"61954db8a48a6ff6cf3e0ed9","totalStars":488,"weapons":[{"weaponId":"60b6ea101ec85acb4193ed15","battleCount":101,"avgStar":2.772277227722772,"winCount":84,"star":280},{"weaponId":"60b6e9c91ec85acb4193cc2f","battleCount":18,"avgStar":2.9444444444444446,"winCount":17,"star":53},{"weaponId":"611258a2d183b274dd8906a4","battleCount":16,"avgStar":2.9375,"winCount":15,"star":47},{"weaponId":"60b6e9fc1ec85acb4193e2ca","battleCount":14,"avgStar":2.7142857142857144,"winCount":10,"star":38},{"weaponId":"6103e6cbaa0079ac7260ef61","battleCount":9,"avgStar":2.4444444444444446,"winCount":5,"star":22},{"weaponId":"60b6ee921ec85acb4195c6e2","battleCount":5,"avgStar":2.4,"winCount":3,"star":12},{"weaponId":"60b6ee421ec85acb41959b68","battleCount":3,"avgStar":3,"winCount":3,"star":9},{"weaponId":"60b6ee421ec85acb41959b34","battleCount":3,"avgStar":3,"winCount":3,"star":9},{"weaponId":"60b6f8a31ec85acb4199ece5","battleCount":3,"avgStar":3,"winCount":3,"star":9},{"weaponId":"60b6ec6e1ec85acb4194dbe2","battleCount":3,"avgStar":3,"winCount":3,"star":9}]},{"battleCount":166,"winCount":142,"artifactSetBuildId":"61954db1a48a6ff6cf3e082e","totalStars":472,"weapons":[{"weaponId":"60b6ea101ec85acb4193ed15","battleCount":74,"avgStar":2.8513513513513513,"winCount":63,"star":211},{"weaponId":"611258a2d183b274dd8906a4","battleCount":37,"avgStar":2.8378378378378377,"winCount":32,"star":105},{"weaponId":"60b6e9c91ec85acb4193cc2f","battleCount":22,"avgStar":2.727272727272727,"winCount":17,"star":60},{"weaponId":"60b6ee921ec85acb4195c6e2","battleCount":12,"avgStar":2.8333333333333335,"winCount":10,"star":34},{"weaponId":"60b6e9fc1ec85acb4193e2c9","battleCount":9,"avgStar":3,"winCount":9,"star":27},{"weaponId":"6103e6cbaa0079ac7260ef61","battleCount":6,"avgStar":3,"winCount":6,"star":18},{"weaponId":"616644a7d28d8641387f7aaa","battleCount":3,"avgStar":2.6666666666666665,"winCount":2,"star":8},{"weaponId":"60b6e9fc1ec85acb4193e2ca","battleCount":3,"avgStar":3,"winCount":3,"star":9}]},{"battleCount":166,"winCount":142,"artifactSetBuildId":"61954db5a48a6ff6cf3e0a1f","totalStars":468,"weapons":[{"weaponId":"611258a2d183b274dd8906a4","battleCount":61,"avgStar":2.8688524590163933,"winCount":54,"star":175},{"weaponId":"60b6ea101ec85acb4193ed15","battleCount":53,"avgStar":2.849056603773585,"winCount":46,"star":151},{"weaponId":"6103e6cbaa0079ac7260ef61","battleCount":13,"avgStar":2.3846153846153846,"winCount":7,"star":31},{"weaponId":"60b6e9c91ec85acb4193cc2f","battleCount":12,"avgStar":2.75,"winCount":10,"star":33},{"weaponId":"60b6f8a31ec85acb4199ece5","battleCount":9,"avgStar":2.888888888888889,"winCount":8,"star":26},{"weaponId":"60b6e9c91ec85acb4193cc36","battleCount":9,"avgStar":3,"winCount":9,"star":27},{"weaponId":"60b6e9fc1ec85acb4193e2ca","battleCount":6,"avgStar":2.6666666666666665,"winCount":5,"star":16},{"weaponId":"60b6ef7d1ec85acb419623ce","battleCount":3,"avgStar":3,"winCount":3,"star":9}]},{"battleCount":139,"winCount":105,"artifactSetBuildId":"61954db6a48a6ff6cf3e0b86","totalStars":370,"weapons":[{"weaponId":"60b6ea101ec85acb4193ed15","battleCount":54,"avgStar":2.7037037037037037,"winCount":43,"star":146},{"weaponId":"60b6e9fc1ec85acb4193e2c9","battleCount":18,"avgStar":2.8333333333333335,"winCount":16,"star":51},{"weaponId":"6103e6cbaa0079ac7260ef61","battleCount":15,"avgStar":2.7333333333333334,"winCount":13,"star":41},{"weaponId":"60b6e9fc1ec85acb4193e2ca","battleCount":15,"avgStar":2.2,"winCount":5,"star":33},{"weaponId":"60b6e9c91ec85acb4193cc2f","battleCount":14,"avgStar":2.642857142857143,"winCount":11,"star":37},{"weaponId":"60b6ee421ec85acb41959b34","battleCount":9,"avgStar":2.5555555555555554,"winCount":6,"star":23},{"weaponId":"611258a2d183b274dd8906a4","battleCount":9,"avgStar":2.888888888888889,"winCount":8,"star":26},{"weaponId":"60b6ec6e1ec85acb4194dbe2","battleCount":5,"avgStar":2.6,"winCount":3,"star":13}]}]}}