{"char_id":"60b6eda01ec85acb41954e7d","constellations":[1729,4324,4835,4441,3515,6769,3102],"builds":[{"weapons":[{"_id":"60b6e9c91ec85acb4193cc61","count":9018},{"_id":"60b6ee601ec85acb4195ac8c","count":3066},{"_id":"60b6f0c41ec85acb4196bebe","count":459},{"_id":"60b6ec6e1ec85acb4194dbe6","count":1319},{"_id":"60b6e9fd1ec85acb4193e2df","count":4425},{"_id":"60b6e9c91ec85acb4193cc8a","count":1037},{"_id":"60b6fe3f1ec85acb419c42f4","count":71},{"_id":"60b6ea101ec85acb4193ecb0","count":3334},{"_id":"60b7295d1ec85acb41ae2f17","count":14},{"_id":"60b6ec6e1ec85acb4194dbdf","count":367},{"_id":"60b6e9c91ec85acb4193cc66","count":311},{"_id":"60b6f23a1ec85acb41976466","count":141},{"_id":"60b6ea101ec85acb4193ecb6","count":939},{"_id":"60b6e9fc1ec85acb4193e2c5","count":144},{"_id":"60b6ee421ec85acb41959b7b","count":62},{"_id":"60b6fc751ec85acb419b8f8c","count":53},{"_id":"60b6eedb1ec85acb4195e458","count":207},{"_id":"60b6fb671ec85acb419b126d","count":6},{"_id":"60db5f46af74591485f5b315","count":28},{"_id":"60f91cbbc582ef2754d92d04","count":20},{"_id":"60b6efcd1ec85acb4196514a","count":16},{"_id":"60f81f4ac582ef2754a2e5cb","count":235},{"_id":"60f9a098c582ef2754f34134","count":137},{"_id":"60b78b001ec85acb41d4c534","count":3},{"_id":"60b6f2081ec85acb41974f13","count":14},{"_id":"61462fff36527efbe7baad42","count":13},{"_id":"6146a63436527efbe7ce9b8b","count":1}],"artifacts":[{"_id":"60b6e9c91ec85acb4193cc4e","activation_number":4}],"count":25440},{"weapons":[{"_id":"60b6e9c91ec85acb4193cc61","count":296},{"_id":"60b6ea101ec85acb4193ecb0","count":56},{"_id":"60b6e9c91ec85acb4193cc8a","count":26},{"_id":"60b6e9fd1ec85acb4193e2df","count":102},{"_id":"60b6ee601ec85acb4195ac8c","count":83},{"_id":"60b6e9fc1ec85acb4193e2c5","count":16},{"_id":"60b6ec6e1ec85acb4194dbdf","count":19},{"_id":"60b6ea101ec85acb4193ecb6","count":68},{"_id":"60b6ec6e1ec85acb4194dbe6","count":26},{"_id":"60b6f0c41ec85acb4196bebe","count":8},{"_id":"60b6f23a1ec85acb41976466","count":9},{"_id":"60b6e9c91ec85acb4193cc66","count":38},{"_id":"60b6eedb1ec85acb4195e458","count":16},{"_id":"60b6fe3f1ec85acb419c42f4","count":17},{"_id":"60f81f4ac582ef2754a2e5cb","count":51},{"_id":"60f91cbbc582ef2754d92d04","count":1},{"_id":"60f9a098c582ef2754f34134","count":7},{"_id":"60b6ee421ec85acb41959b7b","count":8},{"_id":"60b6f2081ec85acb41974f13","count":2},{"_id":"60db5f46af74591485f5b315","count":3},{"_id":"60b7295d1ec85acb41ae2f17","count":1},{"_id":"61462fff36527efbe7baad42","count":3}],"artifacts":[{"_id":"60b6e9c91ec85acb4193cc4c","activation_number":4}],"count":856},{"weapons":[{"_id":"60b6ea101ec85acb4193ecb6","count":28},{"_id":"60b6ea101ec85acb4193ecb0","count":64},{"_id":"60b6e9c91ec85acb4193cc61","count":133},{"_id":"60b6e9fd1ec85acb4193e2df","count":72},{"_id":"60b6ee601ec85acb4195ac8c","count":21},{"_id":"60b6e9c91ec85acb4193cc66","count":6},{"_id":"60b6fb671ec85acb419b126d","count":2},{"_id":"60b6ec6e1ec85acb4194dbdf","count":11},{"_id":"60b6fe3f1ec85acb419c42f4","count":4},{"_id":"60b6e9c91ec85acb4193cc8a","count":32},{"_id":"60b6f23a1ec85acb41976466","count":7},{"_id":"60b6ec6e1ec85acb4194dbe6","count":16},{"_id":"60b6f0c41ec85acb4196bebe","count":3},{"_id":"60f9a098c582ef2754f34134","count":3},{"_id":"60b6eedb1ec85acb4195e458","count":2},{"_id":"60f81f4ac582ef2754a2e5cb","count":3},{"_id":"60b6e9fc1ec85acb4193e2c5","count":5},{"_id":"60f91cbbc582ef2754d92d04","count":1},{"_id":"60b6efcd1ec85acb4196514a","count":1},{"_id":"60b6ee421ec85acb41959b7b","count":1},{"_id":"61462fff36527efbe7baad42","count":3}],"artifacts":[{"_id":"60b6e9c91ec85acb4193cc81","activation_number":4}],"count":418},{"weapons":[{"_id":"60b6e9fd1ec85acb4193e2df","count":26},{"_id":"60b6e9c91ec85acb4193cc8a","count":16},{"_id":"60b6e9c91ec85acb4193cc61","count":115},{"_id":"60b6ec6e1ec85acb4194dbdf","count":21},{"_id":"60b6ea101ec85acb4193ecb6","count":65},{"_id":"60b6ee601ec85acb4195ac8c","count":27},{"_id":"60b6e9fc1ec85acb4193e2c5","count":3},{"_id":"60b6f2081ec85acb41974f13","count":5},{"_id":"60b6ea101ec85acb4193ecb0","count":27},{"_id":"60b6f23a1ec85acb41976466","count":5},{"_id":"60b6fe3f1ec85acb419c42f4","count":3},{"_id":"60f9a098c582ef2754f34134","count":6},{"_id":"60b6ec6e1ec85acb4194dbe6","count":23},{"_id":"60b6ee421ec85acb41959b7b","count":2},{"_id":"60f81f4ac582ef2754a2e5cb","count":3},{"_id":"60b6efcd1ec85acb4196514a","count":1},{"_id":"60b6e9c91ec85acb4193cc66","count":4},{"_id":"60b78b001ec85acb41d4c534","count":1},{"_id":"60b6fb671ec85acb419b126d","count":1},{"_id":"61462fff36527efbe7baad42","count":3},{"_id":"60b7295d1ec85acb41ae2f17","count":1},{"_id":"60f91cbbc582ef2754d92d04","count":1}],"artifacts":[{"_id":"60b6e9c91ec85acb4193cca6","activation_number":4}],"count":359},{"weapons":[{"_id":"60b6e9c91ec85acb4193cc61","count":121},{"_id":"60b6ee601ec85acb4195ac8c","count":31},{"_id":"60b6ea101ec85acb4193ecb0","count":28},{"_id":"60b6e9fd1ec85acb4193e2df","count":49},{"_id":"60b6ec6e1ec85acb4194dbe6","count":11},{"_id":"60b6ea101ec85acb4193ecb6","count":11},{"_id":"60b6f0c41ec85acb4196bebe","count":9},{"_id":"60b6e9c91ec85acb4193cc8a","count":6},{"_id":"60b6fe3f1ec85acb419c42f4","count":6},{"_id":"60b6e9c91ec85acb4193cc66","count":3},{"_id":"60b6ee421ec85acb41959b7b","count":2},{"_id":"60b6ec6e1ec85acb4194dbdf","count":6},{"_id":"60b6fc751ec85acb419b8f8c","count":1},{"_id":"60b6eedb1ec85acb4195e458","count":1},{"_id":"60f81f4ac582ef2754a2e5cb","count":4},{"_id":"60b6e9fc1ec85acb4193e2c5","count":1},{"_id":"60b6f23a1ec85acb41976466","count":1}],"artifacts":[{"_id":"60b6e9c91ec85acb4193cc75","activation_number":4}],"count":291},{"weapons":[{"_id":"60b6e9c91ec85acb4193cc61","count":55},{"_id":"60b6fc751ec85acb419b8f8c","count":1},{"_id":"60b6ec6e1ec85acb4194dbdf","count":14},{"_id":"60b6e9fd1ec85acb4193e2df","count":20},{"_id":"60b6e9c91ec85acb4193cc8a","count":12},{"_id":"60b6ee601ec85acb4195ac8c","count":9},{"_id":"60b6fe3f1ec85acb419c42f4","count":2},{"_id":"60b6ea101ec85acb4193ecb6","count":16},{"_id":"60b6ea101ec85acb4193ecb0","count":32},{"_id":"60b6ec6e1ec85acb4194dbe6","count":12},{"_id":"60f81f4ac582ef2754a2e5cb","count":2},{"_id":"60b6e9c91ec85acb4193cc66","count":3},{"_id":"60f9a098c582ef2754f34134","count":3},{"_id":"60b6f2081ec85acb41974f13","count":1},{"_id":"60b6f0c41ec85acb4196bebe","count":3},{"_id":"60b6ee421ec85acb41959b7b","count":1},{"_id":"60b6e9fc1ec85acb4193e2c5","count":3},{"_id":"60b6f23a1ec85acb41976466","count":1}],"artifacts":[{"_id":"60b6e9c91ec85acb4193cc4e","activation_number":2},{"_id":"60b6e9c91ec85acb4193cca6","activation_number":2}],"count":190},{"weapons":[{"_id":"60b6f23a1ec85acb41976466","count":2},{"_id":"60b6e9c91ec85acb4193cc61","count":35},{"_id":"60b6e9c91ec85acb4193cc66","count":5},{"_id":"60b6ea101ec85acb4193ecb0","count":28},{"_id":"60b6e9fd1ec85acb4193e2df","count":8},{"_id":"60b6e9fc1ec85acb4193e2c5","count":4},{"_id":"60b6e9c91ec85acb4193cc8a","count":5},{"_id":"60b6ec6e1ec85acb4194dbdf","count":4},{"_id":"60b6ee421ec85acb41959b7b","count":3},{"_id":"60b6efcd1ec85acb4196514a","count":1},{"_id":"60b6fe3f1ec85acb419c42f4","count":1},{"_id":"60f9a098c582ef2754f34134","count":4},{"_id":"60b6ea101ec85acb4193ecb6","count":5},{"_id":"60b6eedb1ec85acb4195e458","count":2},{"_id":"60b6ec6e1ec85acb4194dbe6","count":5},{"_id":"60b6f0c41ec85acb4196bebe","count":4},{"_id":"60b6ee601ec85acb4195ac8c","count":10},{"_id":"60f81f4ac582ef2754a2e5cb","count":2}],"artifacts":[{"_id":"60b6e9c91ec85acb4193cc4c","activation_number":2},{"_id":"60b6e9c91ec85acb4193cc4e","activation_number":2}],"count":128},{"weapons":[{"_id":"60b6e9fd1ec85acb4193e2df","count":14},{"_id":"60b6ea101ec85acb4193ecb0","count":16},{"_id":"60b6e9c91ec85acb4193cc61","count":39},{"_id":"60b6e9c91ec85acb4193cc8a","count":5},{"_id":"60b6ec6e1ec85acb4194dbdf","count":7},{"_id":"60b6ec6e1ec85acb4194dbe6","count":8},{"_id":"60b6e9c91ec85acb4193cc66","count":5},{"_id":"60b6ea101ec85acb4193ecb6","count":16},{"_id":"60b6ee601ec85acb4195ac8c","count":11},{"_id":"60b6eedb1ec85acb4195e458","count":2},{"_id":"60f9a098c582ef2754f34134","count":2},{"_id":"60b6f2081ec85acb41974f13","count":1},{"_id":"60b6e9fc1ec85acb4193e2c5","count":1},{"_id":"61462fff36527efbe7baad42","count":1}],"artifacts":[{"_id":"60b6e9c91ec85acb4193cc4c","activation_number":2},{"_id":"60b6e9c91ec85acb4193cca6","activation_number":2}],"count":128}],"teams":[{"party":["60b6eda01ec85acb41954e37","60b6eda01ec85acb41954e6e","60b6eda01ec85acb41954e7d","612ef177a73e7789e100ab36"],"count":7890},{"party":["60b6eda01ec85acb41954e6e","60b6eda01ec85acb41954e7d","60b6eda01ec85acb41954f0b","60db015aaf74591485e062f6"],"count":2396},{"party":["60b6eda01ec85acb41954e37","60b6eda01ec85acb41954e7d","60b6edd41ec85acb419565c6","60b6ede91ec85acb4195729c"],"count":1415},{"party":["60b6eda01ec85acb41954e6e","60b6eda01ec85acb41954e7d","60b6edd41ec85acb4195658b","60b6ede91ec85acb4195729c"],"count":1401},{"party":["60b6eda01ec85acb41954e7d","60b6ede91ec85acb41957255","60b6ede91ec85acb4195729c","612ef177a73e7789e100ab36"],"count":1400},{"party":["60b6eda01ec85acb41954e7d","60db015aaf74591485e062f6","612ef177a73e7789e100ab36","612f1ed6a73e7789e108d8dd"],"count":1231},{"party":["60b6eda01ec85acb41954df1","60b6eda01ec85acb41954e37","60b6eda01ec85acb41954e7d","60b6ede91ec85acb4195729c"],"count":1187},{"party":["60b6eda01ec85acb41954e37","60b6eda01ec85acb41954e6e","60b6eda01ec85acb41954e7d","60db015aaf74591485e062f6"],"count":1148},{"party":["60b6eda01ec85acb41954e7d","60b6eda01ec85acb41954ed9","60b6ede91ec85acb419571ea","60b6ede91ec85acb4195729c"],"count":1099},{"party":["60b6eda01ec85acb41954e6e","60b6eda01ec85acb41954e7d","60b6eda01ec85acb41954f0b","60b6ede91ec85acb4195725a"],"count":1060},{"party":["60b6eda01ec85acb41954e37","60b6eda01ec85acb41954e7d","60b6edd41ec85acb419565c6","60db015aaf74591485e062f6"],"count":1045},{"party":["60b6eda01ec85acb41954df1","60b6eda01ec85acb41954e37","60b6eda01ec85acb41954e7d","60db015aaf74591485e062f6"],"count":995},{"party":["60b6eda01ec85acb41954e6e","60b6eda01ec85acb41954e7d","60db015aaf74591485e062f6","612ef177a73e7789e100ab36"],"count":982},{"party":["60b6eda01ec85acb41954df1","60b6eda01ec85acb41954e37","60b6eda01ec85acb41954e7d","60b6eda01ec85acb41954ed9"],"count":964},{"party":["60b6eda01ec85acb41954e37","60b6eda01ec85acb41954e6e","60b6eda01ec85acb41954e7d","60b6ede91ec85acb4195725a"],"count":891},{"party":["60b6eda01ec85acb41954e7d","60b6ede91ec85acb419571ea","60b6ede91ec85acb4195725a","60b6ede91ec85acb4195729c"],"count":851},{"party":["60b6eda01ec85acb41954df1","60b6eda01ec85acb41954e37","60b6eda01ec85acb41954e7d","60b6ede91ec85acb4195725a"],"count":719},{"party":["60b6eda01ec85acb41954e6e","60b6eda01ec85acb41954e7d","60b6eda01ec85acb41954ed9","60b6edd41ec85acb4195658b"],"count":696},{"party":["60b6eda01ec85acb41954e6e","60b6eda01ec85acb41954e7d","60b6eda01ec85acb41954f0b","612ef177a73e7789e100ab36"],"count":641},{"party":["60b6eda01ec85acb41954e37","60b6eda01ec85acb41954e7d","60db015aaf74591485e062f6","612ef177a73e7789e100ab36"],"count":616},{"party":["60b6eda01ec85acb41954e37","60b6eda01ec85acb41954e7d","60b6edd41ec85acb419565c6","60b6ede91ec85acb4195725a"],"count":583},{"party":["60b6eda01ec85acb41954e4e","60b6eda01ec85acb41954e7d","60b6ede91ec85acb41957255","612ef177a73e7789e100ab36"],"count":560},{"party":["60b6eda01ec85acb41954e6e","60b6eda01ec85acb41954e7d","60b6eda01ec85acb41954f0b","60b6ede91ec85acb4195729c"],"count":554},{"party":["60b6eda01ec85acb41954e6e","60b6eda01ec85acb41954e7d","60b6eda01ec85acb41954ed9","60b6eda01ec85acb41954f0b"],"count":516},{"party":["60b6eda01ec85acb41954e7d","60b6ede91ec85acb419571ea","60b6ede91ec85acb4195729c","60db015aaf74591485e062f6"],"count":515},{"party":["60b6eda01ec85acb41954e7d","60b6ede91ec85acb419571ea","60b6ede91ec85acb41957206","60b6ede91ec85acb4195729c"],"count":500},{"party":["60b6eda01ec85acb41954e6e","60b6eda01ec85acb41954e7d","60b6eda01ec85acb41954ed9","60b6ede91ec85acb419571ea"],"count":486},{"party":["60b6eda01ec85acb41954e37","60b6eda01ec85acb41954e7d","60b6ede91ec85acb4195729c","61125ec7d183b274dd8a3ec1"],"count":474},{"party":["60b6eda01ec85acb41954e6e","60b6eda01ec85acb41954e7d","60b6ede91ec85acb419571ea","60b6ede91ec85acb4195729c"],"count":438},{"party":["60b6eda01ec85acb41954e7d","60b6eda01ec85acb41954ed9","60b6edd41ec85acb4195658b","60b6ede91ec85acb4195729c"],"count":436},{"party":["60b6eda01ec85acb41954e7d","60b6edd41ec85acb4195658b","60b6ede91ec85acb4195729c","60db015aaf74591485e062f6"],"count":425},{"party":["60b6eda01ec85acb41954e6e","60b6eda01ec85acb41954e7d","60b6eda01ec85acb41954ed9","612ef177a73e7789e100ab36"],"count":417},{"party":["60b6eda01ec85acb41954e37","60b6eda01ec85acb41954e7d","60b6eda01ec85acb41954ed9","60b6edd41ec85acb419565c6"],"count":407},{"party":["60b6eda01ec85acb41954e4e","60b6eda01ec85acb41954e6e","60b6eda01ec85acb41954e7d","60b6edd41ec85acb4195658b"],"count":404},{"party":["60b6eda01ec85acb41954e7d","60b6ede91ec85acb419571ea","60b6ede91ec85acb4195729c","612ef177a73e7789e100ab36"],"count":402},{"party":["60b6eda01ec85acb41954e37","60b6eda01ec85acb41954e4e","60b6eda01ec85acb41954e7d","60f7b5a3c582ef2754907a27"],"count":401},{"party":["60b6eda01ec85acb41954e7d","60b6ede91ec85acb4195729c","60db015aaf74591485e062f6","612ef177a73e7789e100ab36"],"count":397},{"party":["60b6eda01ec85acb41954e6e","60b6eda01ec85acb41954e7d","60b6ede91ec85acb4195729c","60b6ee171ec85acb4195883f"],"count":388},{"party":["60b6eda01ec85acb41954e37","60b6eda01ec85acb41954e7d","60b6edd41ec85acb419565c6","612ef177a73e7789e100ab36"],"count":388},{"party":["60b6eda01ec85acb41954e6e","60b6eda01ec85acb41954e7d","60b6ede91ec85acb4195725a","612ef177a73e7789e100ab36"],"count":387},{"party":["60b6eda01ec85acb41954e37","60b6eda01ec85acb41954e7d","61125ec7d183b274dd8a3ec1","612ef177a73e7789e100ab36"],"count":376},{"party":["60b6eda01ec85acb41954e37","60b6eda01ec85acb41954e7d","60db015aaf74591485e062f6","61125ec7d183b274dd8a3ec1"],"count":366},{"party":["60b6eda01ec85acb41954e7d","60b6ede91ec85acb4195729c","61125ec7d183b274dd8a3ec1","612ef177a73e7789e100ab36"],"count":365},{"party":["60b6eda01ec85acb41954e7d","60b6ede91ec85acb419571ea","60b6ede91ec85acb4195729c","60b6ee621ec85acb4195b0ee"],"count":361},{"party":["60b6eda01ec85acb41954e6e","60b6eda01ec85acb41954e7d","60b6ede91ec85acb4195729c","612ef177a73e7789e100ab36"],"count":351},{"party":["60b6eda01ec85acb41954e6e","60b6eda01ec85acb41954e7d","612ef177a73e7789e100ab36","612f1ed6a73e7789e108d8dd"],"count":349},{"party":["60b6eda01ec85acb41954e37","60b6eda01ec85acb41954e7d","60b6eda01ec85acb41954ed9","60f7b5a3c582ef2754907a27"],"count":343},{"party":["60b6eda01ec85acb41954e7d","60b6eda01ec85acb41954ed9","60b6ede91ec85acb4195729c","60b6ee171ec85acb4195883f"],"count":342},{"party":["60b6eda01ec85acb41954df1","60b6eda01ec85acb41954e37","60b6eda01ec85acb41954e7d","612ef177a73e7789e100ab36"],"count":340}],"total":27810}