{"char_id":"60b6eda01ec85acb41954e23","constellations":[51,176,277,427,524,552,4354],"builds":[{"weapons":[{"_id":"60b6e9c91ec85acb4193cbdd","count":2096},{"_id":"60b6e9fd1ec85acb4193e2e4","count":397},{"_id":"60b6ef7d1ec85acb41962403","count":252},{"_id":"60b6e9c91ec85acb4193cc0c","count":223},{"_id":"60b6ee421ec85acb41959b33","count":218},{"_id":"60b6e9c91ec85acb4193cbe6","count":118},{"_id":"60b6ec581ec85acb4194cee4","count":92},{"_id":"60b6ea101ec85acb4193ed28","count":68},{"_id":"60b6ea101ec85acb4193ecf8","count":63},{"_id":"60b6f3561ec85acb4197d6fa","count":38},{"_id":"60b6e9c91ec85acb4193cc4a","count":31},{"_id":"60b6ec581ec85acb4194cf04","count":20}],"artifacts":[{"_id":"60b6ea101ec85acb4193ed4f","activation_number":4}],"count":3691},{"weapons":[{"_id":"60b6e9c91ec85acb4193cbdd","count":794},{"_id":"60b6e9fd1ec85acb4193e2e4","count":287},{"_id":"60b6ef7d1ec85acb41962403","count":159},{"_id":"60b6e9c91ec85acb4193cc0c","count":154},{"_id":"60b6e9c91ec85acb4193cbe6","count":75},{"_id":"60b6ee421ec85acb41959b33","count":69},{"_id":"60b6ea101ec85acb4193ed28","count":58},{"_id":"60b6ec581ec85acb4194cee4","count":45},{"_id":"60b6ea101ec85acb4193ecf8","count":21},{"_id":"60b6e9c91ec85acb4193cc4a","count":21},{"_id":"60b6ec581ec85acb4194cf04","count":16},{"_id":"60b6f39f1ec85acb4197f436","count":13},{"_id":"60b6f3561ec85acb4197d6fa","count":13},{"_id":"60b6ef7d1ec85acb419623b1","count":9}],"artifacts":[{"_id":"60b6e9c91ec85acb4193cca6","activation_number":4}],"count":1755},{"weapons":[{"_id":"60b6e9c91ec85acb4193cbdd","count":135},{"_id":"60b6ee421ec85acb41959b33","count":25},{"_id":"60b6ef7d1ec85acb41962403","count":21},{"_id":"60b6ec581ec85acb4194cee4","count":19},{"_id":"60b6f3561ec85acb4197d6fa","count":7},{"_id":"60b6e9c91ec85acb4193cc0c","count":5},{"_id":"60b6e9c91ec85acb4193cc4a","count":5},{"_id":"60b6ec581ec85acb4194cf04","count":4},{"_id":"60b6e9fd1ec85acb4193e2e4","count":4},{"_id":"60b6ec581ec85acb4194cee5","count":3},{"_id":"60b7083b1ec85acb41a05553","count":3},{"_id":"60b6e9c91ec85acb4193cbe6","count":3},{"_id":"60b6f39f1ec85acb4197f436","count":3}],"artifacts":[{"_id":"60b6e9c91ec85acb4193cc81","activation_number":4}],"count":238},{"weapons":[{"_id":"60b6e9c91ec85acb4193cbdd","count":29},{"_id":"60b6ee421ec85acb41959b33","count":19},{"_id":"60b6ef7d1ec85acb41962403","count":10},{"_id":"60b6ec581ec85acb4194cee4","count":4},{"_id":"60b6ec581ec85acb4194cf04","count":4},{"_id":"60b6f3561ec85acb4197d6fa","count":4},{"_id":"60b6e9c91ec85acb4193cbe6","count":4},{"_id":"60b6e9fd1ec85acb4193e2e4","count":4},{"_id":"60b6e9c91ec85acb4193cc0c","count":3},{"_id":"60b7083b1ec85acb41a05553","count":3}],"artifacts":[{"_id":"60b6e9c91ec85acb4193cf13","activation_number":4}],"count":90},{"weapons":[{"_id":"60b6e9c91ec85acb4193cbdd","count":47},{"_id":"60b6ee421ec85acb41959b33","count":8},{"_id":"60b6ef7d1ec85acb41962403","count":5},{"_id":"60b6e9fd1ec85acb4193e2e4","count":5},{"_id":"60b6ec581ec85acb4194cee4","count":3},{"_id":"60b6e9c91ec85acb4193cbe6","count":3},{"_id":"60b6ea101ec85acb4193ecf8","count":3}],"artifacts":[{"_id":"60b6e9c91ec85acb4193cca6","activation_number":2},{"_id":"60b6ea101ec85acb4193ed4f","activation_number":2}],"count":82},{"weapons":[{"_id":"60b6e9c91ec85acb4193cbdd","count":37},{"_id":"60b6ee421ec85acb41959b33","count":15},{"_id":"60b6ef7d1ec85acb41962403","count":7},{"_id":"60b6e9fd1ec85acb4193e2e4","count":6},{"_id":"60b6e9c91ec85acb4193cbe6","count":4},{"_id":"60b6ec581ec85acb4194cee4","count":4},{"_id":"60b6e9c91ec85acb4193cc0c","count":4}],"artifacts":[{"_id":"60b6ec581ec85acb4194cf65","activation_number":4}],"count":81},{"weapons":[{"_id":"60b6e9c91ec85acb4193cbdd","count":25},{"_id":"60b6ee421ec85acb41959b33","count":16},{"_id":"60b6ec581ec85acb4194cee4","count":4},{"_id":"60b6ef7d1ec85acb41962403","count":3},{"_id":"60b6e9c91ec85acb4193cc4a","count":3}],"artifacts":[{"_id":"60b6ea101ec85acb4193ed4f","activation_number":2},{"_id":"60b6ec581ec85acb4194cf65","activation_number":2}],"count":60},{"weapons":[{"_id":"60b6e9c91ec85acb4193cbdd","count":30},{"_id":"60b6ec581ec85acb4194cee4","count":9}],"artifacts":[{"_id":"60b6e9c91ec85acb4193cc81","activation_number":2},{"_id":"60b6ea101ec85acb4193ed4f","activation_number":2}],"count":44},{"weapons":[{"_id":"60b6e9c91ec85acb4193cbdd","count":12},{"_id":"60b6ee421ec85acb41959b33","count":6},{"_id":"60b6e9c91ec85acb4193cc0c","count":5},{"_id":"60b6ef7d1ec85acb41962403","count":4},{"_id":"60b6ec581ec85acb4194cee4","count":3}],"artifacts":[{"_id":"60b6e9c91ec85acb4193cca6","activation_number":2},{"_id":"60b6ec581ec85acb4194cf65","activation_number":2}],"count":35}],"teams":[{"party":["60b6eda01ec85acb41954e23","60b6eda01ec85acb41954e37","60b6edd41ec85acb419565c6","60b6ede91ec85acb4195729c"],"count":114},{"party":["60b6eda01ec85acb41954e23","60b6eda01ec85acb41954e37","60b6edd41ec85acb419565c6","60b6ede91ec85acb4195725a"],"count":93},{"party":["60b6eda01ec85acb41954e23","60b6edd41ec85acb4195658b","60b6edd41ec85acb419565c6","60b6ede91ec85acb4195729c"],"count":91},{"party":["60b6eda01ec85acb41954e23","60b6eda01ec85acb41954e37","60b6eda01ec85acb41954ed9","60b6edd41ec85acb419565c6"],"count":65},{"party":["60b6eda01ec85acb41954e23","60b6ede91ec85acb4195729c","60b6ee171ec85acb4195883f","60b6ee621ec85acb4195b0ee"],"count":63},{"party":["60b6eda01ec85acb41954e23","60b6eda01ec85acb41954e37","60b6eda01ec85acb41954e7d","60b6edd41ec85acb419565c6"],"count":61},{"party":["60b6eda01ec85acb41954e23","60b6edd41ec85acb4195658b","60b6edd41ec85acb419565c6","60b6ede91ec85acb4195725a"],"count":60},{"party":["60b6eda01ec85acb41954e23","60b6eda01ec85acb41954e37","60b6edd41ec85acb419565c6","60b6ee621ec85acb4195b0ee"],"count":55}],"total":6076}