{"artifactSetId":"60b6e9c91ec85acb4193cc75","artifactSetBuilds":[{"artifactSetBuildId":"61954db1a48a6ff6cf3e082b","count":30502,"battleCount":38061,"winCount":32796,"avgStar":2.8304038254381125,"characters":[{"characterId":"60b6eda01ec85acb41954e1b","count":17878},{"characterId":"60b6eda01ec85acb41954ef6","count":6934},{"characterId":"60b6eda01ec85acb41954e99","count":5284},{"characterId":"612ef177a73e7789e100ab36","count":2903},{"characterId":"60b6eda01ec85acb41954e7d","count":1253},{"characterId":"612f1ed6a73e7789e108d8dd","count":1109},{"characterId":"60b6ee441ec85acb4195a268","count":398},{"characterId":"60b6eda01ec85acb41954ee8","count":109}]},{"artifactSetBuildId":"61954db5a48a6ff6cf3e09cd","count":8646,"battleCount":7890,"winCount":6866,"avgStar":2.839923954372624,"characters":[{"characterId":"60b6eda01ec85acb41954e1b","count":3729},{"characterId":"60b6eda01ec85acb41954ef6","count":2300},{"characterId":"60b6eda01ec85acb41954e99","count":1462},{"characterId":"612f1ed6a73e7789e108d8dd","count":108},{"characterId":"60b6ee441ec85acb4195a268","count":54}]},{"artifactSetBuildId":"61954db1a48a6ff6cf3e0870","count":2047,"battleCount":1173,"winCount":993,"avgStar":2.812446717817562,"characters":[{"characterId":"60b6eda01ec85acb41954ef6","count":261},{"characterId":"60b6ee441ec85acb4195a268","count":28}]},{"artifactSetBuildId":"61954db5a48a6ff6cf3e0a0b","count":1474,"battleCount":1089,"winCount":979,"avgStar":2.874196510560147,"characters":[{"characterId":"60b6eda01ec85acb41954e99","count":532},{"characterId":"612f1ed6a73e7789e108d8dd","count":127}]},{"artifactSetBuildId":"61954db7a48a6ff6cf3e0cc9","count":1124,"battleCount":900,"winCount":795,"avgStar":2.858888888888889,"characters":[]},{"artifactSetBuildId":"61954dc0a48a6ff6cf3e179c","count":552,"battleCount":417,"winCount":353,"avgStar":2.800959232613909,"characters":[]},{"artifactSetBuildId":"61954db9a48a6ff6cf3e0fc2","count":414,"battleCount":501,"winCount":416,"avgStar":2.7964071856287425,"characters":[{"characterId":"612ef177a73e7789e100ab36","count":387}]},{"artifactSetBuildId":"61954db8a48a6ff6cf3e0ead","count":286,"battleCount":200,"winCount":164,"avgStar":2.785,"characters":[]},{"artifactSetBuildId":"61954dc3a48a6ff6cf3e1b3c","count":137,"battleCount":91,"winCount":62,"avgStar":2.5824175824175826,"characters":[]},{"artifactSetBuildId":"61954deca48a6ff6cf3e46ab","count":105,"battleCount":77,"winCount":63,"avgStar":2.7532467532467533,"characters":[]},{"artifactSetBuildId":"61954dc0a48a6ff6cf3e16e9","count":78,"battleCount":134,"winCount":110,"avgStar":2.791044776119403,"characters":[]},{"artifactSetBuildId":"61954e0fa48a6ff6cf3e688e","count":29,"battleCount":17,"winCount":13,"avgStar":2.6470588235294117,"characters":[]},{"artifactSetBuildId":"61954dcaa48a6ff6cf3e2321","count":21,"battleCount":3,"winCount":3,"avgStar":3,"characters":[]},{"artifactSetBuildId":"61954e03a48a6ff6cf3e5d23","count":21,"battleCount":22,"winCount":20,"avgStar":2.909090909090909,"characters":[]},{"artifactSetBuildId":"6195505ea48a6ff6cf3fea0c","count":21,"battleCount":9,"winCount":6,"avgStar":2.5555555555555554,"characters":[]},{"artifactSetBuildId":"61954ea7a48a6ff6cf3edc1e","count":15,"battleCount":6,"winCount":6,"avgStar":3,"characters":[]},{"artifactSetBuildId":"61954e15a48a6ff6cf3e6e89","count":13,"battleCount":6,"winCount":3,"avgStar":2.5,"characters":[]},{"artifactSetBuildId":"61954fa3a48a6ff6cf3f6fb3","count":12,"battleCount":6,"winCount":6,"avgStar":3,"characters":[]},{"artifactSetBuildId":"619552e2a48a6ff6cf418c2f","count":12,"battleCount":2,"winCount":1,"avgStar":2.5,"characters":[]},{"artifactSetBuildId":"61954ed4a48a6ff6cf3ef591","count":10,"battleCount":9,"winCount":6,"avgStar":2.5555555555555554,"characters":[]},{"artifactSetBuildId":"61954fd4a48a6ff6cf3f96f0","count":6,"battleCount":6,"winCount":4,"avgStar":2.5,"characters":[]},{"artifactSetBuildId":"6195524ea48a6ff6cf4131d8","count":5,"battleCount":10,"winCount":5,"avgStar":2.4,"characters":[]}]}